[
  {
    "class": "SyntaxError",
    "message": "Unexpected token 'g', \"ges/MFR721\"... is not valid JSON\n  Deserialization error: to see the raw response, inspect the hidden field {error}.$response on this object.",
    "stack": [
      "pages/api/sold-route.js:12",
      "pages/api/sold-route.js:107"
    ]
  },
  {
    "class": "SyntaxError",
    "message": "Unexpected token 'g', \"ges/MFR721\"... is not valid JSON\n  Deserialization error: to see the raw response, inspect the hidden field {error}.$response on this object.",
    "stack": [
      "pages/api/sold-route.js:26",
      "pages/api/sold-route.js:12",
      "pages/api/sold-route.js:107"
    ]
  }
]